build/lib/build/lib/build/lib/build/lib/build/lib/build/lib/build/lib/examples/prepare_worst_case.py
build/lib/build/lib/build/lib/build/lib/build/lib/build/lib/build/lib/examples/qsch_editor_example.py
build/lib/build/lib/build/lib/build/lib/build/lib/build/lib/build/lib/examples/qspice_example.py
build/lib/build/lib/build/lib/build/lib/build/lib/build/lib/build/lib/examples/run_montecarlo.py
build/lib/build/lib/build/lib/build/lib/build/lib/build/lib/build/lib/qspice/__init__.py
build/lib/build/lib/build/lib/build/lib/build/lib/build/lib/build/lib/qspice/qspice.py
build/lib/build/lib/build/lib/build/lib/build/lib/build/lib/build/lib/qspice/sim/sim_runner.py
build/lib/build/lib/build/lib/build/lib/build/lib/build/lib/examples/prepare_worst_case.py
build/lib/build/lib/build/lib/build/lib/build/lib/build/lib/examples/qsch_editor_example.py
build/lib/build/lib/build/lib/build/lib/build/lib/build/lib/examples/qspice_example.py
build/lib/build/lib/build/lib/build/lib/build/lib/build/lib/examples/run_montecarlo.py
build/lib/build/lib/build/lib/build/lib/build/lib/build/lib/qspice/__init__.py
build/lib/build/lib/build/lib/build/lib/build/lib/build/lib/qspice/qspice.py
build/lib/build/lib/build/lib/build/lib/build/lib/build/lib/qspice/sim/sim_runner.py
build/lib/build/lib/build/lib/build/lib/build/lib/examples/prepare_worst_case.py
build/lib/build/lib/build/lib/build/lib/build/lib/examples/qsch_editor_example.py
build/lib/build/lib/build/lib/build/lib/build/lib/examples/qspice_example.py
build/lib/build/lib/build/lib/build/lib/build/lib/examples/run_montecarlo.py
build/lib/build/lib/build/lib/build/lib/build/lib/qspice/__init__.py
build/lib/build/lib/build/lib/build/lib/build/lib/qspice/qspice.py
build/lib/build/lib/build/lib/build/lib/build/lib/qspice/sim/sim_runner.py
build/lib/build/lib/build/lib/build/lib/examples/prepare_worst_case.py
build/lib/build/lib/build/lib/build/lib/examples/qsch_editor_example.py
qspice-1.0.1.dist-info/licenses/LICENSE
qspice-1.0.1.dist-info/METADATA
qspice-1.0.1.dist-info/WHEEL
qspice-1.0.1.dist-info/top_level.txt
qspice-1.0.1.dist-info/RECORD
