Metadata-Version: 2.4
Name: qspice
Version: 1.0.1
Summary: A set of tools to operate with QSPICE
Author-email: Nuno Brum <me@nunobrum.com>
License-Expression: GPL-3.0
Classifier: Programming Language :: Python :: 3
Classifier: Operating System :: OS Independent
Requires-Python: >=3.9
License-File: LICENSE
Requires-Dist: spicelib>=1.4.5
Dynamic: license-file
